LICENSE
pacsanini/__init__.py
pacsanini/__main__.py
pacsanini/__version__.py
pacsanini/cli/__init__.py
pacsanini/cli/base.py
pacsanini/cli/commands.py
pacsanini/cli/config.py
pacsanini/cli/dashboard.py
pacsanini/cli/db.py
pacsanini/cli/net.py
pacsanini/cli/parse.py
pacsanini/cli/pipeline.py
pacsanini/config.py
pacsanini/convert.py
pacsanini/dashboard/__init__.py
pacsanini/dashboard/app.py
pacsanini/dashboard/assets/base.css
pacsanini/dashboard/assets/dashboard.css
pacsanini/dashboard/env.py
pacsanini/db/__init__.py
pacsanini/db/crud.py
pacsanini/db/dcm2model.py
pacsanini/db/migrate.py
pacsanini/db/migrations/README
pacsanini/db/migrations/alembic.ini
pacsanini/db/migrations/env.py
pacsanini/db/migrations/script.py.mako
pacsanini/db/migrations/versions/eef30b8456eb_initial_configuration.py
pacsanini/db/models.py
pacsanini/db/parser.py
pacsanini/db/utils.py
pacsanini/db/views.py
pacsanini/errors.py
pacsanini/io/__init__.py
pacsanini/io/base_parser.py
pacsanini/io/df_parser.py
pacsanini/io/io_parsers.py
pacsanini/models.py
pacsanini/net/__init__.py
pacsanini/net/c_echo.py
pacsanini/net/c_find.py
pacsanini/net/c_move.py
pacsanini/net/c_store.py
pacsanini/net/storescp.py
pacsanini/parse.py
pacsanini/pipeline/__init__.py
pacsanini/pipeline/notifications.py
pacsanini/pipeline/orchestra.py
pacsanini/pipeline/tasks.py
pacsanini/utils.py
pacsanini-0.2.1.dist-info/entry_points.txt
pacsanini-0.2.1.dist-info/LICENSES/PYDANTIC_LICENSE
pacsanini-0.2.1.dist-info/LICENSES/PANDAS_LICENSE
pacsanini-0.2.1.dist-info/LICENSES/CLICK_LICENSE
pacsanini-0.2.1.dist-info/LICENSES/PYYAML_LICENSE
pacsanini-0.2.1.dist-info/LICENSES/SQLALCHEMY_UTILS_LICENSE
pacsanini-0.2.1.dist-info/LICENSE
pacsanini-0.2.1.dist-info/LICENSES/SQLALCHEMY_LICENSE
pacsanini-0.2.1.dist-info/LICENSES/PYDICOM_LICENSE
pacsanini-0.2.1.dist-info/LICENSES/DASH_LICENSE
pacsanini-0.2.1.dist-info/LICENSES/LOGURU_LICENSE
pacsanini-0.2.1.dist-info/LICENSES/PREFECT_LICENSE
pacsanini-0.2.1.dist-info/LICENSES/PYNETDICOM_LICENSE
pacsanini-0.2.1.dist-info/LICENSES/ALEMBIC_LICENSE
pacsanini-0.2.1.dist-info/WHEEL
pacsanini-0.2.1.dist-info/METADATA
pacsanini-0.2.1.dist-info/RECORD
