Metadata-Version: 2.1
Name: pacsanini
Version: 0.2.1
Summary: A package for DICOM utilities.
License: Apache 2.0
Keywords: DICOM,PACS,medical imagery
Author: Aurélien Chick
Author-email: achick@therapixel.com
Maintainer: Aurélien Chick
Maintainer-email: achick@therapixel.com
Requires-Python: >=3.7.1,<4.0.0
Classifier: Development Status :: 4 - Beta
Classifier: Intended Audience :: Developers
Classifier: License :: OSI Approved :: Apache Software License
Classifier: License :: Other/Proprietary License
Classifier: Programming Language :: Python :: 3
Classifier: Programming Language :: Python :: 3 :: Only
Classifier: Programming Language :: Python :: 3.10
Classifier: Programming Language :: Python :: 3.7
Classifier: Programming Language :: Python :: 3.8
Classifier: Programming Language :: Python :: 3.9
Classifier: Topic :: Software Development :: Build Tools
Requires-Dist: PyYAML (>=5.4)
Requires-Dist: SQLAlchemy-Utils (>=0.37.8,<0.38.0)
Requires-Dist: SQLAlchemy[mypy] (>=1.4.22,<2.0.0)
Requires-Dist: alembic (>=1.7.4,<2.0.0)
Requires-Dist: click (>=7.1.2,<8.0.0)
Requires-Dist: dash (>=2.0.0,<3.0.0)
Requires-Dist: loguru (>=0.5.3,<0.6.0)
Requires-Dist: pandas (>=1.2.4,<2.0.0)
Requires-Dist: prefect (>=0.15.6,<0.16.0)
Requires-Dist: pydantic (>=1.7.4)
Requires-Dist: pydicom (>=2.1.2,<3.0.0)
Requires-Dist: pynetdicom (>=1.5.7,<2.0.0)
